ffsendclient/__init__.py
ffsendclient/ffsendclient.py
ffsendclient-1.1.dist-info/LICENSE
ffsendclient-1.1.dist-info/METADATA
ffsendclient-1.1.dist-info/WHEEL
ffsendclient-1.1.dist-info/top_level.txt
ffsendclient-1.1.dist-info/RECORD
