Metadata-Version: 2.1
Name: ffsendclient
Version: 1.1
Summary: A library for interfacing with Firefox Send <https://send.firefox.com/> or your own instance of it.
Home-page: https://gitlab.com/skorov/ffsendclient
Author: Alexei Doudkine
Author-email: alexei@volkis.com.au
License: UNKNOWN
Platform: UNKNOWN
Classifier: Programming Language :: Python :: 3 :: Only
Classifier: License :: OSI Approved :: Apache Software License
Classifier: Operating System :: OS Independent
Requires-Python: >=3.6
Requires-Dist: requests
Requires-Dist: pycryptodome
Requires-Dist: websockets
